README.txt
setup.py
decoupage/__init__.py
decoupage/cli.py
decoupage/create_index.py
decoupage/factory.py
decoupage/formats.py
decoupage/formatters.py
decoupage/index.py
decoupage/templates.py
decoupage/utils.py
decoupage/web.py
decoupage.egg-info/PKG-INFO
decoupage.egg-info/SOURCES.txt
decoupage.egg-info/dependency_links.txt
decoupage.egg-info/entry_points.txt
decoupage.egg-info/not-zip-safe
decoupage.egg-info/requires.txt
decoupage.egg-info/top_level.txt