Metadata-Version: 1.0
Name: decoupage
Version: 0.14.2
Summary: Decoupage is the art of decorating an object by gluing colored paper cutouts onto it in combination with special paint effects ... The software decoupage lets you stitch together index pages from filesystem content
Home-page: http://k0s.org/hg/decoupage
Author: Jeff Hammel
Author-email: k0scist@gmail.com
License: GPL
Platform: UNKNOWN
